cdk_prb/__init__.py
cdk_prb/py.typed
cdk_prb/_jsii/__init__.py
cdk_prb/_jsii/cdk-pull-request-builder@0.2.0.jsii.tgz
cdk_prb-0.2.0.dist-info/METADATA
cdk_prb-0.2.0.dist-info/WHEEL
cdk_prb-0.2.0.dist-info/top_level.txt
cdk_prb-0.2.0.dist-info/RECORD
